[
  {
    "No": 10001,
    "Kr": "매직미사일",
    "En": ""
  },
  {
    "No": 10002,
    "Kr": "파이어볼",
    "En": ""
  },
  {
    "No": 10003,
    "Kr": "아이스스피어",
    "En": ""
  },
  {
    "No": 10004,
    "Kr": "체인라이트닝",
    "En": ""
  },
  {
    "No": 10005,
    "Kr": "애시드볼",
    "En": ""
  },
  {
    "No": 10101,
    "Kr": "빠른 속도로 공격하는 기본 스킬",
    "En": ""
  },
  {
    "No": 10102,
    "Kr": "적중 시 단일 피해와 주변 몬스터 폭발 피해",
    "En": ""
  },
  {
    "No": 10103,
    "Kr": "적중 시 몬스터의 이동속도를 감소",
    "En": ""
  },
  {
    "No": 10104,
    "Kr": " {0}마리의 몬스터를 튕기며 피해주고 일정 확률로 적 기절",
    "En": ""
  },
  {
    "No": 10105,
    "Kr": "적중 시 단일 피해와 주변 몬스터를 중독시키는 독 안개를 발생",
    "En": ""
  },
  {
    "No": 11001,
    "Kr": "매직미사일 공격력 <color=#2DFC16>+{0}%</color> 증가",
    "En": ""
  },
  {
    "No": 11002,
    "Kr": "매직미사일 시전 투사체 <color=#00FFFF>+{0}</color> 증가",
    "En": ""
  },
  {
    "No": 11003,
    "Kr": "매직미사일 공격 쿨다운 <color=#00FFFF>-{0}%</color> 감소 ",
    "En": ""
  },
  {
    "No": 11004,
    "Kr": "매직미사일 관통 확률 <color=#00FFFF>+{0}%</color> 증가 \\n<color=#BF77FF>현재 확률 {1}%</color>",
    "En": ""
  },
  {
    "No": 12001,
    "Kr": "파이어볼 공격력 <color=#2DFC16>+{0}%</color> 증가 \\n폭발 공격력 <color=#2DFC16>+{1}%</color> 증가",
    "En": ""
  },
  {
    "No": 12002,
    "Kr": "파이어볼 투사체 <color=#00FFFF>+{0}</color> 증가",
    "En": ""
  },
  {
    "No": 12003,
    "Kr": "파이어볼 시전 쿨다운 <color=#00FFFF>-{0}%</color> 감소",
    "En": ""
  },
  {
    "No": 12004,
    "Kr": "파이어볼 폭발 범위 <color=#FF8C00>+{0}%</color> 증가",
    "En": ""
  },
  {
    "No": 13001,
    "Kr": "아이스스피어 공격력 <color=#2DFC16>+{0}%</color> 증가",
    "En": ""
  },
  {
    "No": 13002,
    "Kr": "아이스스피어 투사체 <color=#00FFFF>+{0}</color> 증가",
    "En": ""
  },
  {
    "No": 13003,
    "Kr": "아이스스피어 시전 쿨다운 <color=#00FFFF>-{0}%</color> 감소",
    "En": ""
  },
  {
    "No": 13004,
    "Kr": "아이스스피어 둔화 <color=#FFD200>+{0}%</color> 증가 \\n<color=#BF77FF>현재 둔화율 {1}%</color>",
    "En": ""
  },
  {
    "No": 14001,
    "Kr": "체인라이트닝 공격력 <color=#2DFC16>+{0}%</color> 증가",
    "En": ""
  },
  {
    "No": 14002,
    "Kr": "체인라이트닝 타겟 수 <color=#00FFFF>+{0}</color> 증가",
    "En": ""
  },
  {
    "No": 14003,
    "Kr": "체인라이트닝 시전 쿨다운 <color=#00FFFF>-{0}초</color> 감소",
    "En": ""
  },
  {
    "No": 14004,
    "Kr": "체인라이트닝 스턴 확률 <color=#00FFFF>+{0}%</color> 증가 \\n<color=#BF77FF>현재 확률 {1}%</color>",
    "En": ""
  },
  {
    "No": 15001,
    "Kr": "애시드볼 공격력 <color=#2DFC16>+{0}%</color> \\n중독 공격력 <color=#2DFC16>+{1}%</color> 증가",
    "En": ""
  },
  {
    "No": 15002,
    "Kr": "애시드볼 투사체 <color=#00FFFF>+{0}</color> 증가",
    "En": ""
  },
  {
    "No": 15003,
    "Kr": "애시드볼 시전 쿨다운 <color=#00FFFF>-{0}</color> 감소",
    "En": ""
  },
  {
    "No": 15004,
    "Kr": "애시드볼 독 안개 범위 <color=#FF8C00>+{0}</color> 증가",
    "En": ""
  }
]